langstat/__init__.py
langstat/__main__.py
langstat/clargs.py
langstat/scrape.py
langstat/urls.py
langstat-1.2.0.dist-info/DESCRIPTION.rst
langstat-1.2.0.dist-info/METADATA
langstat-1.2.0.dist-info/RECORD
langstat-1.2.0.dist-info/WHEEL
langstat-1.2.0.dist-info/metadata.json
langstat-1.2.0.dist-info/top_level.txt
