Metadata-Version: 2.0
Name: langstat
Version: 1.2.0
Summary: Finds most common words for a language
Home-page: https://github.com/Fylipp/lang-stat
Author: Philipp Ploder
Author-email: UNKNOWN
License: UNKNOWN
Keywords: opensubtitles
Platform: UNKNOWN
Classifier: Development Status :: 5 - Production/Stable
Classifier: License :: OSI Approved :: MIT License
Classifier: Programming Language :: Python :: 3
Requires-Dist: pysrt
Requires-Dist: requests
Requires-Dist: lxml
Requires-Dist: ostd
